fpyutils/__init__.py
fpyutils/exceptions.py
fpyutils/filelines.py
fpyutils/notify.py
fpyutils/path.py
fpyutils/shell.py
fpyutils-4.0.0.dist-info/LICENSE.txt
fpyutils-4.0.0.dist-info/METADATA
fpyutils-4.0.0.dist-info/WHEEL
fpyutils-4.0.0.dist-info/top_level.txt
fpyutils-4.0.0.dist-info/RECORD
