Metadata-Version: 2.1
Name: fpyutils
Version: 4.0.0
Summary: A collection of useful non-standard Python functions which aim to be simple to use, highly readable but not efficient.
Home-page: https://blog.franco.net.eu.org/software/#fpyutils
Author: Franco Masotti
Author-email: franco.masotti@tutanota.com
License: GPLv3+
Keywords: utilities,text,command
Classifier: Development Status :: 5 - Production/Stable
Classifier: Intended Audience :: Developers
Classifier: Topic :: Software Development :: Libraries
Classifier: License :: OSI Approved :: GNU General Public License v3 or later (GPLv3+)
Classifier: Programming Language :: Python :: 3
Requires-Python: <4,>=3.8
License-File: LICENSE.txt
